sdnorm/__init__.py
sdnorm/evaluation.py
sdnorm/general_utils.py
sdnorm/scripts/__init__.py
sdnorm/scripts/create_density_template.py
sdnorm/scripts/run_evaluation.py
sdnorm/scripts/run_sdnorm.py
sdnorm/scripts/sdnorm_prune.py
sdnorm/sdnorm.py
sdnorm/streamline_utils.py
sdnorm-0.1.1.dist-info/LICENSE
sdnorm-0.1.1.dist-info/METADATA
sdnorm-0.1.1.dist-info/WHEEL
sdnorm-0.1.1.dist-info/entry_points.txt
sdnorm-0.1.1.dist-info/RECORD
