Metadata-Version: 2.3
Name: SDNorm
Version: 0.1.1
Summary: Streamline Density Normalization
License: MIT
Author: Yixue Feng
Requires-Python: >=3.9,<4.0
Classifier: License :: OSI Approved :: MIT License
Classifier: Programming Language :: Python :: 3
Classifier: Programming Language :: Python :: 3.9
Classifier: Programming Language :: Python :: 3.10
Classifier: Programming Language :: Python :: 3.11
Classifier: Programming Language :: Python :: 3.12
Classifier: Programming Language :: Python :: 3.13
Requires-Dist: antspyx (>=0.5.4,<0.6.0)
Requires-Dist: cvxpy (>=1.6.5,<2.0.0)
Requires-Dist: dipy (>=1.7.0,<2.0.0)
Requires-Dist: fury (>=0.9.0,<0.10.0)
Requires-Dist: matplotlib (>=3.7.0,<4.0.0)
Requires-Dist: nibabel (>=5.1.0,<6.0.0)
Requires-Dist: numpy (>=1.25.0,<2.0.0)
Requires-Dist: pandas (>=2.1.0,<3.0.0)
Requires-Dist: scipy (>=1.11.0,<2.0.0)
Project-URL: Homepage, https://github.com/wendyfyx/SDNorm
Project-URL: Repository, https://github.com/wendyfyx/SDNorm
